joetorch/__init__.py
joetorch/datasets/__init__.py
joetorch/datasets/dataset.py
joetorch/datasets/imagenet.py
joetorch/datasets/mnist.py
joetorch/functional/__init__.py
joetorch/functional/loss_functions.py
joetorch/functional/positional_embeddings.py
joetorch/functional/representations.py
joetorch/nn/__init__.py
joetorch/nn/convmixer.py
joetorch/nn/mnist.py
joetorch/nn/stable_diffusion.py
joetorch/nn/modules/__init__.py
joetorch/nn/modules/attention.py
joetorch/nn/modules/convolutional.py
joetorch/nn/modules/fully_connected.py
joetorch/optim/__init__.py
joetorch/optim/optim.py
joetorch/optim/schedule.py
joetorch/optim/train.py
joetorch-0.0.42.dist-info/METADATA
joetorch-0.0.42.dist-info/WHEEL
joetorch-0.0.42.dist-info/top_level.txt
joetorch-0.0.42.dist-info/RECORD
