Metadata-Version: 2.4
Name: joetorch
Version: 0.0.42
Summary: Useful code for testing new Deep Learning algorithms.
Author-email: Joe Griffith <joeagriffith@gmail.com>
Classifier: Programming Language :: Python :: 3
Classifier: License :: OSI Approved :: MIT License
Classifier: Operating System :: OS Independent
Requires-Python: >=3.7
Requires-Dist: numpy>=1.19.2
